autosh/__init__.py
autosh/config-template.toml
autosh/config.py
autosh/main.py
autosh/session.py
autosh/plugins/__init__.py
autosh/plugins/calc.py
autosh/plugins/cli.py
autosh/plugins/clock.py
autosh/plugins/code.py
autosh/plugins/search.py
autosh/plugins/web.py
autosh-0.0.9.dist-info/METADATA
autosh-0.0.9.dist-info/WHEEL
autosh-0.0.9.dist-info/entry_points.txt
autosh-0.0.9.dist-info/licenses/LICENSE
autosh-0.0.9.dist-info/RECORD
