Metadata-Version: 2.4
Name: autosh
Version: 0.0.9
Summary: The AI-powered, noob-friendly interactive shell
Author-email: Wenyu Zhao <wenyuzhaox@gmail.com>
License-Expression: MIT
License-File: LICENSE
Keywords: agent,chatgpt,cli,command line,gpt,interactive,llm,openai,openrouter,shell,terminal
Requires-Python: >=3.12
Requires-Dist: agentia>=0.0.8
Requires-Dist: asyncio>=3.4.3
Requires-Dist: markdownify>=1.1.0
Requires-Dist: neongrid>=0.0.3
Requires-Dist: prompt-toolkit>=3.0.51
Requires-Dist: pydantic>=2.11.3
Requires-Dist: python-dotenv>=1.1.0
Requires-Dist: rich>=14.0.0
Requires-Dist: tavily-python>=0.5.4
Requires-Dist: typer>=0.12.5
Requires-Dist: tzlocal>=5.3.1
